{
    "name": "Angela Davis",
    "age": 0,
    "address": {
        "street": "Derrick Fall",
        "city": "Dianamouth",
        "state": "Louisiana",
        "zip": "91571"
    },
    "contact": {
        "phone": "332-905-0235x5835",
        "servicePhone": "800957655"
    },
    "birthday": "2025-14-05",
    "ip": "214.246.226.6",
    "foo": "bar",
    "profile": {
        "about": "Range point challenge light her employee page. Present wall program argue kid.\nRecord home avoid score her help pay place. Thousand choose wide present. Pay everyone close front step.",
        "bio": "Several others teacher cold citizen able. Teacher expert around family mouth win. He truth through election chance concern."
    },
    "currency": [
        "ILS",
        "Israeli new shekel"
    ]
}